neon_speech/__init__.py
neon_speech/__main__.py
neon_speech/cli.py
neon_speech/service.py
neon_speech/stt.py
neon_speech/transformers.py
neon_speech/utils.py
neon_speech-4.5.0.dist-info/LICENSE.md
neon_speech-4.5.0.dist-info/METADATA
neon_speech-4.5.0.dist-info/WHEEL
neon_speech-4.5.0.dist-info/entry_points.txt
neon_speech-4.5.0.dist-info/top_level.txt
neon_speech-4.5.0.dist-info/RECORD
