Metadata-Version: 2.1
Name: neon-speech
Version: 4.5.0
Summary: Neon Speech Module
Home-page: https://github.com/NeonGeckoCom/neon_speech
Author: Neongecko
Author-email: developers@neon.ai
License: BSD-3-Clause
License-File: LICENSE.md
Requires-Dist: ovos-dinkum-listener~=0.2
Requires-Dist: ovos-bus-client>=0.0.3,~=0.0
Requires-Dist: ovos-utils>=0.0.30,~=0.0
Requires-Dist: ovos-plugin-manager~=0.1
Requires-Dist: click~=8.0
Requires-Dist: click-default-group~=1.2
Requires-Dist: neon-utils[audio,network,signal]>=1.12.1,~=1.12
Requires-Dist: ovos-config>=0.0.7,~=0.0
Requires-Dist: ovos-vad-plugin-webrtcvad~=0.0.1
Requires-Dist: ovos-ww-plugin-vosk~=0.1
Requires-Dist: ovos-microphone-plugin-alsa~=0.1
Provides-Extra: docker
Requires-Dist: ovos-stt-plugin-vosk~=0.1; extra == "docker"
Requires-Dist: neon-stt-plugin-nemo~=0.1; extra == "docker"
Requires-Dist: onnxruntime!=1.16.0; extra == "docker"
Requires-Dist: ovos-ww-plugin-pocketsphinx~=0.1; extra == "docker"
Requires-Dist: ovos-ww-plugin-precise-lite~=0.1; extra == "docker"
Requires-Dist: ovos-ww-plugin-precise~=0.1; extra == "docker"
